README.md
setup.py
src/pymonitor_foretls.egg-info/PKG-INFO
src/pymonitor_foretls.egg-info/SOURCES.txt
src/pymonitor_foretls.egg-info/dependency_links.txt
src/pymonitor_foretls.egg-info/not-zip-safe
src/pymonitor_foretls.egg-info/top_level.txt
src/pymonitoring/PyMonitoring.py
src/pymonitoring/__init__.py
src/pymonitoring/pymonitor.py