Metadata-Version: 2.1
Name: pymonitor-foretls
Version: 0.1.0
Summary: pymonitoring like pytest just for monitoring
Home-page: https://github.com/noahgrad/pymonitor
Author: Noa gradovitch
Author-email: noahgrad@gmail.com
License: UNKNOWN
Platform: UNKNOWN
Requires-Python: >=3.7
